area_codes/__init__.py
area_codes/area_codes.py
area_codes/data_types.py
area_codes/state_data.py
py_area_codes-0.1.1.dist-info/METADATA
py_area_codes-0.1.1.dist-info/WHEEL
py_area_codes-0.1.1.dist-info/top_level.txt
py_area_codes-0.1.1.dist-info/RECORD
